unitable/__init__.py
unitable-0.0.2.dist-info/LICENSE
unitable-0.0.2.dist-info/METADATA
unitable-0.0.2.dist-info/WHEEL
unitable-0.0.2.dist-info/top_level.txt
unitable-0.0.2.dist-info/RECORD
