Metadata-Version: 2.1
Name: unitable
Version: 0.0.2
Summary: A data analysis environment that unites the best features of pandas, R, Stata, and others.
Home-page: https://github.com/mhowison/unitable
Author: Mark Howison
Author-email: mark@howison.org
License: BSD
Keywords: data,data analysis,data frame,data science
Classifier: Development Status :: 3 - Alpha
Classifier: License :: OSI Approved :: BSD License
Classifier: Intended Audience :: Science/Research
Classifier: Natural Language :: English
Classifier: Programming Language :: Python :: 3
Classifier: Topic :: Scientific/Engineering
Provides: unitable
License-File: LICENSE
Requires-Dist: pandas
